pyroll/gripping_analysis.py
pyroll_gripping_analysis-3.0.1.dist-info/METADATA
pyroll_gripping_analysis-3.0.1.dist-info/WHEEL
pyroll_gripping_analysis-3.0.1.dist-info/licenses/LICENSE
pyroll_gripping_analysis-3.0.1.dist-info/RECORD
