Metadata-Version: 2.3
Name: pyroll-gripping-analysis
Version: 3.0.1
Summary: Plugin for PyRoll calculating and analysing the geometric gripping condition.
Author-email: Christoph Renzing <christoph.renzing@imf.tu-freiberg.de>
Requires-Python: <4.0,>=3.9
Requires-Dist: pyroll-core~=3.0
Requires-Dist: pyroll-interface-friction~=3.0
